dragon/__init__.py
dragon/search_algorithm/__init__.py
dragon/search_algorithm/hyperband.py
dragon/search_algorithm/mutant_ucb.py
dragon/search_algorithm/search_algorithm.py
dragon/search_algorithm/ssea.py
dragon/search_operators/__init__.py
dragon/search_operators/addons.py
dragon/search_operators/base_neighborhoods.py
dragon/search_operators/crossover.py
dragon/search_operators/dag_neighborhoods.py
dragon/search_space/__init__.py
dragon/search_space/base_variables.py
dragon/search_space/bricks_variables.py
dragon/search_space/dag_encoding.py
dragon/search_space/dag_variables.py
dragon/search_space/bricks/__init__.py
dragon/search_space/bricks/attention.py
dragon/search_space/bricks/basics.py
dragon/search_space/bricks/convolutions.py
dragon/search_space/bricks/dropout.py
dragon/search_space/bricks/normalization.py
dragon/search_space/bricks/pooling.py
dragon/search_space/bricks/recurrences.py
dragon/utils/__init__.py
dragon/utils/exceptions.py
dragon/utils/plot_functions.py
dragon/utils/tools.py
dragon_autodl-1.1.dist-info/LICENSE.txt
dragon_autodl-1.1.dist-info/METADATA
dragon_autodl-1.1.dist-info/WHEEL
dragon_autodl-1.1.dist-info/top_level.txt
dragon_autodl-1.1.dist-info/RECORD
