Metadata-Version: 2.1
Name: dragon_autodl
Version: 1.1
Summary: Implementation of the algorithmic framework from <An algorithmic framework for the optimization of deep neural networks architectures and hyperparameters>
Home-page: https://github.com/JulieKeisler/DRAGON
Author: Julie Keisler
Author-email: julie.keisler.rfo@gmail.com
Project-URL: Bug Tracker, https://github.com/JulieKeisler/DRAGON/issues
Keywords: deep learning,neural networks,automl,neural architecture search,hyperparameters optimization,metaheuristics
Classifier: Programming Language :: Python :: 3
Classifier: License :: CeCILL-C Free Software License Agreement (CECILL-C)
Classifier: Operating System :: OS Independent
Requires-Python: >=3.9
License-File: LICENSE.txt
Requires-Dist: numpy<2.0.0
Requires-Dist: pandas
Requires-Dist: torch
Requires-Dist: graphviz
Provides-Extra: mpi
Requires-Dist: mpi4py>=3.1.2; extra == "mpi"
Provides-Extra: docs
Requires-Dist: Sphinx>=3.0.0; extra == "docs"
Requires-Dist: docutils; extra == "docs"
Requires-Dist: pylons-sphinx-themes>=1.0.8; extra == "docs"
Requires-Dist: pylons_sphinx_latesturl; extra == "docs"
Requires-Dist: repoze.sphinx.autointerface; extra == "docs"
Requires-Dist: sphinxcontrib-autoprogram; extra == "docs"
Requires-Dist: sphinx-copybutton; extra == "docs"
Requires-Dist: sphinx-tabs; extra == "docs"
Requires-Dist: sphinx-panels; extra == "docs"
Requires-Dist: sphinx-rtd-theme; extra == "docs"
Requires-Dist: pillow>=6.2.0; extra == "docs"
Requires-Dist: openml; extra == "docs"
Requires-Dist: optuna; extra == "docs"
Requires-Dist: matplotlib; extra == "docs"
Requires-Dist: skorch; extra == "docs"
